pocketbase/__init__.py
pocketbase/client.py
pocketbase/models/__init__.py
pocketbase/models/admin.py
pocketbase/models/collection.py
pocketbase/models/external_auth.py
pocketbase/models/file_upload.py
pocketbase/models/log_request.py
pocketbase/models/record.py
pocketbase/models/utils/__init__.py
pocketbase/models/utils/base_model.py
pocketbase/models/utils/list_result.py
pocketbase/models/utils/schema_field.py
pocketbase/services/__init__.py
pocketbase/services/admin_service.py
pocketbase/services/collection_service.py
pocketbase/services/log_service.py
pocketbase/services/realtime_service.py
pocketbase/services/record_service.py
pocketbase/services/settings_service.py
pocketbase/services/utils/__init__.py
pocketbase/services/utils/base_crud_service.py
pocketbase/services/utils/base_service.py
pocketbase/services/utils/crud_service.py
pocketbase/services/utils/sse.py
pocketbase/stores/__init__.py
pocketbase/stores/base_auth_store.py
pocketbase/stores/local_auth_store.py
pocketbase/utils.py
pocketbasex-0.8.2.dist-info/METADATA
pocketbasex-0.8.2.dist-info/WHEEL
pocketbasex-0.8.2.dist-info/RECORD
