Metadata-Version: 2.1
Name: pocketbasex
Version: 0.8.2
Summary: PocketBase SDK for python.
Home-page: https://github.com/abyesilyurt/pocketbase
Keywords: pocketbase,sdk
Author: Aziz Berkay Yesilyurt
Author-email: abyesilyurt@gmail.com
Requires-Python: >=3.7,<4.0
Classifier: Programming Language :: Python :: 3
Classifier: Programming Language :: Python :: 3.7
Classifier: Programming Language :: Python :: 3.8
Classifier: Programming Language :: Python :: 3.9
Classifier: Programming Language :: Python :: 3.10
Classifier: Programming Language :: Python :: 3.11
Requires-Dist: httpx (>=0.23.0,<0.24.0)
Project-URL: Bug Tracker, https://github.com/abyesilyurt/pocketbase/issues
Project-URL: Repository, https://github.com/abyesilyurt/pocketbase
